{
  "slug": "the-rooftop-garden-plan",
  "title": "The Rooftop Garden Plan",
  "title_ko": "옥상 정원 계획",
  "level": "A2",
  "ageBand": "8-10",
  "summary_ko": "비어 있던 옥상을 작은 정원으로 바꾸기 위해 아이들이 계획하고 역할을 나누는 이야기예요.",
  "pages": [
    {
      "sentences": [
        {
          "text": "Our apartment rooftop was wide, sunny, and completely empty.",
          "translation_ko": "우리 아파트 옥상은 넓고 햇빛이 좋았지만 완전히 비어 있었어요.",
          "audio": "/seed/the-rooftop-garden-plan/audio/p1-s1.mp3",
          "wordTimings": [
            {
              "word": "Our",
              "charStart": 0,
              "charEnd": 3,
              "startMs": 0,
              "endMs": 360
            },
            {
              "word": "apartment",
              "charStart": 4,
              "charEnd": 13,
              "startMs": 360,
              "endMs": 860
            },
            {
              "word": "rooftop",
              "charStart": 14,
              "charEnd": 21,
              "startMs": 860,
              "endMs": 1400
            },
            {
              "word": "was",
              "charStart": 22,
              "charEnd": 25,
              "startMs": 1400,
              "endMs": 1800
            },
            {
              "word": "wide",
              "charStart": 26,
              "charEnd": 30,
              "startMs": 1800,
              "endMs": 2320
            },
            {
              "word": "sunny",
              "charStart": 32,
              "charEnd": 37,
              "startMs": 2820,
              "endMs": 2820
            },
            {
              "word": "and",
              "charStart": 39,
              "charEnd": 42,
              "startMs": 3260,
              "endMs": 3480
            },
            {
              "word": "completely",
              "charStart": 43,
              "charEnd": 53,
              "startMs": 3480,
              "endMs": 3880
            },
            {
              "word": "empty",
              "charStart": 54,
              "charEnd": 59,
              "startMs": 3880,
              "endMs": 4200
            }
          ]
        }
      ]
    },
    {
      "sentences": [
        {
          "text": "We imagined tomatoes, mint, and small yellow flowers up there.",
          "translation_ko": "우리는 그곳에 토마토와 민트, 작은 노란 꽃을 상상했어요.",
          "audio": "/seed/the-rooftop-garden-plan/audio/p2-s1.mp3",
          "wordTimings": [
            {
              "word": "We",
              "charStart": 0,
              "charEnd": 2,
              "startMs": 0,
              "endMs": 280
            },
            {
              "word": "imagined",
              "charStart": 3,
              "charEnd": 11,
              "startMs": 280,
              "endMs": 760
            },
            {
              "word": "tomatoes",
              "charStart": 12,
              "charEnd": 20,
              "startMs": 760,
              "endMs": 1400
            },
            {
              "word": "mint",
              "charStart": 22,
              "charEnd": 26,
              "startMs": 1940,
              "endMs": 1940
            },
            {
              "word": "and",
              "charStart": 28,
              "charEnd": 31,
              "startMs": 2280,
              "endMs": 2540
            },
            {
              "word": "small",
              "charStart": 32,
              "charEnd": 37,
              "startMs": 2540,
              "endMs": 2740
            },
            {
              "word": "yellow",
              "charStart": 38,
              "charEnd": 44,
              "startMs": 2740,
              "endMs": 3000
            },
            {
              "word": "flowers",
              "charStart": 45,
              "charEnd": 52,
              "startMs": 3000,
              "endMs": 3320
            },
            {
              "word": "up",
              "charStart": 53,
              "charEnd": 55,
              "startMs": 3320,
              "endMs": 3580
            },
            {
              "word": "there",
              "charStart": 56,
              "charEnd": 61,
              "startMs": 3580,
              "endMs": 3760
            }
          ]
        }
      ]
    },
    {
      "sentences": [
        {
          "text": "The first problem was the wind, which pushed every light pot aside.",
          "translation_ko": "첫 문제는 바람이었고, 가벼운 화분들을 모두 밀어냈어요.",
          "audio": "/seed/the-rooftop-garden-plan/audio/p3-s1.mp3",
          "wordTimings": [
            {
              "word": "The",
              "charStart": 0,
              "charEnd": 3,
              "startMs": 0,
              "endMs": 220
            },
            {
              "word": "first",
              "charStart": 4,
              "charEnd": 9,
              "startMs": 220,
              "endMs": 540
            },
            {
              "word": "problem",
              "charStart": 10,
              "charEnd": 17,
              "startMs": 540,
              "endMs": 920
            },
            {
              "word": "was",
              "charStart": 18,
              "charEnd": 21,
              "startMs": 920,
              "endMs": 1160
            },
            {
              "word": "the",
              "charStart": 22,
              "charEnd": 25,
              "startMs": 1160,
              "endMs": 1400
            },
            {
              "word": "wind",
              "charStart": 26,
              "charEnd": 30,
              "startMs": 1400,
              "endMs": 1600
            },
            {
              "word": "which",
              "charStart": 32,
              "charEnd": 37,
              "startMs": 2100,
              "endMs": 2220
            },
            {
              "word": "pushed",
              "charStart": 38,
              "charEnd": 44,
              "startMs": 2220,
              "endMs": 2480
            },
            {
              "word": "every",
              "charStart": 45,
              "charEnd": 50,
              "startMs": 2480,
              "endMs": 2960
            },
            {
              "word": "light",
              "charStart": 51,
              "charEnd": 56,
              "startMs": 2960,
              "endMs": 3220
            },
            {
              "word": "pot",
              "charStart": 57,
              "charEnd": 60,
              "startMs": 3220,
              "endMs": 3440
            },
            {
              "word": "aside",
              "charStart": 61,
              "charEnd": 66,
              "startMs": 3440,
              "endMs": 3860
            }
          ]
        }
      ]
    },
    {
      "sentences": [
        {
          "text": "So we chose heavy clay pots and placed them near the low wall.",
          "translation_ko": "그래서 우리는 무거운 진흙 화분을 고르고 낮은 벽 근처에 놓았어요.",
          "audio": "/seed/the-rooftop-garden-plan/audio/p4-s1.mp3",
          "wordTimings": [
            {
              "word": "So",
              "charStart": 0,
              "charEnd": 2,
              "startMs": 0,
              "endMs": 220
            },
            {
              "word": "we",
              "charStart": 3,
              "charEnd": 5,
              "startMs": 220,
              "endMs": 420
            },
            {
              "word": "chose",
              "charStart": 6,
              "charEnd": 11,
              "startMs": 420,
              "endMs": 680
            },
            {
              "word": "heavy",
              "charStart": 12,
              "charEnd": 17,
              "startMs": 680,
              "endMs": 1020
            },
            {
              "word": "clay",
              "charStart": 18,
              "charEnd": 22,
              "startMs": 1020,
              "endMs": 1280
            },
            {
              "word": "pots",
              "charStart": 23,
              "charEnd": 27,
              "startMs": 1280,
              "endMs": 1620
            },
            {
              "word": "and",
              "charStart": 28,
              "charEnd": 31,
              "startMs": 1620,
              "endMs": 2300
            },
            {
              "word": "placed",
              "charStart": 32,
              "charEnd": 38,
              "startMs": 2300,
              "endMs": 2580
            },
            {
              "word": "them",
              "charStart": 39,
              "charEnd": 43,
              "startMs": 2580,
              "endMs": 2800
            },
            {
              "word": "near",
              "charStart": 44,
              "charEnd": 48,
              "startMs": 2800,
              "endMs": 2920
            },
            {
              "word": "the",
              "charStart": 49,
              "charEnd": 52,
              "startMs": 2920,
              "endMs": 3140
            },
            {
              "word": "low",
              "charStart": 53,
              "charEnd": 56,
              "startMs": 3140,
              "endMs": 3340
            },
            {
              "word": "wall",
              "charStart": 57,
              "charEnd": 61,
              "startMs": 3340,
              "endMs": 3620
            }
          ]
        }
      ]
    },
    {
      "sentences": [
        {
          "text": "The second problem was carrying water up two flights of stairs.",
          "translation_ko": "두 번째 문제는 물을 계단 두 층 위로 나르는 일이었어요.",
          "audio": "/seed/the-rooftop-garden-plan/audio/p5-s1.mp3",
          "wordTimings": [
            {
              "word": "The",
              "charStart": 0,
              "charEnd": 3,
              "startMs": 0,
              "endMs": 200
            },
            {
              "word": "second",
              "charStart": 4,
              "charEnd": 10,
              "startMs": 200,
              "endMs": 540
            },
            {
              "word": "problem",
              "charStart": 11,
              "charEnd": 18,
              "startMs": 540,
              "endMs": 920
            },
            {
              "word": "was",
              "charStart": 19,
              "charEnd": 22,
              "startMs": 920,
              "endMs": 1200
            },
            {
              "word": "carrying",
              "charStart": 23,
              "charEnd": 31,
              "startMs": 1200,
              "endMs": 1500
            },
            {
              "word": "water",
              "charStart": 32,
              "charEnd": 37,
              "startMs": 1500,
              "endMs": 1880
            },
            {
              "word": "up",
              "charStart": 38,
              "charEnd": 40,
              "startMs": 1880,
              "endMs": 2140
            },
            {
              "word": "two",
              "charStart": 41,
              "charEnd": 44,
              "startMs": 2140,
              "endMs": 2460
            },
            {
              "word": "flights",
              "charStart": 45,
              "charEnd": 52,
              "startMs": 2460,
              "endMs": 2720
            },
            {
              "word": "of",
              "charStart": 53,
              "charEnd": 55,
              "startMs": 2720,
              "endMs": 3020
            },
            {
              "word": "stairs",
              "charStart": 56,
              "charEnd": 62,
              "startMs": 3020,
              "endMs": 3280
            }
          ]
        }
      ]
    },
    {
      "sentences": [
        {
          "text": "We made a schedule so nobody had to carry it alone.",
          "translation_ko": "우리는 아무도 혼자 나르지 않도록 순서를 정했어요.",
          "audio": "/seed/the-rooftop-garden-plan/audio/p6-s1.mp3",
          "wordTimings": [
            {
              "word": "We",
              "charStart": 0,
              "charEnd": 2,
              "startMs": 0,
              "endMs": 260
            },
            {
              "word": "made",
              "charStart": 3,
              "charEnd": 7,
              "startMs": 260,
              "endMs": 420
            },
            {
              "word": "a",
              "charStart": 8,
              "charEnd": 9,
              "startMs": 420,
              "endMs": 700
            },
            {
              "word": "schedule",
              "charStart": 10,
              "charEnd": 18,
              "startMs": 700,
              "endMs": 1000
            },
            {
              "word": "so",
              "charStart": 19,
              "charEnd": 21,
              "startMs": 1300,
              "endMs": 1560
            },
            {
              "word": "nobody",
              "charStart": 22,
              "charEnd": 28,
              "startMs": 1560,
              "endMs": 1920
            },
            {
              "word": "had",
              "charStart": 29,
              "charEnd": 32,
              "startMs": 1920,
              "endMs": 2200
            },
            {
              "word": "to",
              "charStart": 33,
              "charEnd": 35,
              "startMs": 2200,
              "endMs": 2600
            },
            {
              "word": "carry",
              "charStart": 36,
              "charEnd": 41,
              "startMs": 2600,
              "endMs": 2600
            },
            {
              "word": "it",
              "charStart": 42,
              "charEnd": 44,
              "startMs": 2600,
              "endMs": 2820
            },
            {
              "word": "alone",
              "charStart": 45,
              "charEnd": 50,
              "startMs": 2820,
              "endMs": 3080
            }
          ]
        }
      ]
    },
    {
      "sentences": [
        {
          "text": "Every Tuesday, I watered the mint and checked the soil.",
          "translation_ko": "매주 화요일 나는 민트에 물을 주고 흙을 확인했어요.",
          "audio": "/seed/the-rooftop-garden-plan/audio/p7-s1.mp3",
          "wordTimings": [
            {
              "word": "Every",
              "charStart": 0,
              "charEnd": 5,
              "startMs": 0,
              "endMs": 340
            },
            {
              "word": "Tuesday",
              "charStart": 6,
              "charEnd": 13,
              "startMs": 340,
              "endMs": 800
            },
            {
              "word": "I",
              "charStart": 15,
              "charEnd": 16,
              "startMs": 1220,
              "endMs": 1380
            },
            {
              "word": "watered",
              "charStart": 17,
              "charEnd": 24,
              "startMs": 1380,
              "endMs": 1700
            },
            {
              "word": "the",
              "charStart": 25,
              "charEnd": 28,
              "startMs": 1700,
              "endMs": 1860
            },
            {
              "word": "mint",
              "charStart": 29,
              "charEnd": 33,
              "startMs": 1860,
              "endMs": 2020
            },
            {
              "word": "and",
              "charStart": 34,
              "charEnd": 37,
              "startMs": 2020,
              "endMs": 2460
            },
            {
              "word": "checked",
              "charStart": 38,
              "charEnd": 45,
              "startMs": 2460,
              "endMs": 2680
            },
            {
              "word": "the",
              "charStart": 46,
              "charEnd": 49,
              "startMs": 2680,
              "endMs": 2980
            },
            {
              "word": "soil",
              "charStart": 50,
              "charEnd": 54,
              "startMs": 2980,
              "endMs": 3160
            }
          ]
        }
      ]
    },
    {
      "sentences": [
        {
          "text": "By the third week, green leaves leaned toward the sun.",
          "translation_ko": "셋째 주가 되자 초록 잎들이 햇빛 쪽으로 기울었어요.",
          "audio": "/seed/the-rooftop-garden-plan/audio/p8-s1.mp3",
          "wordTimings": [
            {
              "word": "By",
              "charStart": 0,
              "charEnd": 2,
              "startMs": 0,
              "endMs": 300
            },
            {
              "word": "the",
              "charStart": 3,
              "charEnd": 6,
              "startMs": 300,
              "endMs": 540
            },
            {
              "word": "third",
              "charStart": 7,
              "charEnd": 12,
              "startMs": 540,
              "endMs": 840
            },
            {
              "word": "week",
              "charStart": 13,
              "charEnd": 17,
              "startMs": 840,
              "endMs": 1200
            },
            {
              "word": "green",
              "charStart": 19,
              "charEnd": 24,
              "startMs": 1580,
              "endMs": 1940
            },
            {
              "word": "leaves",
              "charStart": 25,
              "charEnd": 31,
              "startMs": 1940,
              "endMs": 2280
            },
            {
              "word": "leaned",
              "charStart": 32,
              "charEnd": 38,
              "startMs": 2280,
              "endMs": 2640
            },
            {
              "word": "toward",
              "charStart": 39,
              "charEnd": 45,
              "startMs": 2640,
              "endMs": 2980
            },
            {
              "word": "the",
              "charStart": 46,
              "charEnd": 49,
              "startMs": 2980,
              "endMs": 3260
            },
            {
              "word": "sun",
              "charStart": 50,
              "charEnd": 53,
              "startMs": 3260,
              "endMs": 3460
            }
          ]
        }
      ]
    },
    {
      "sentences": [
        {
          "text": "Neighbors came upstairs to smell the fresh herbs.",
          "translation_ko": "이웃들이 신선한 허브 냄새를 맡으러 옥상에 올라왔어요.",
          "audio": "/seed/the-rooftop-garden-plan/audio/p9-s1.mp3",
          "wordTimings": [
            {
              "word": "Neighbors",
              "charStart": 0,
              "charEnd": 9,
              "startMs": 0,
              "endMs": 660
            },
            {
              "word": "came",
              "charStart": 10,
              "charEnd": 14,
              "startMs": 660,
              "endMs": 960
            },
            {
              "word": "upstairs",
              "charStart": 15,
              "charEnd": 23,
              "startMs": 960,
              "endMs": 1520
            },
            {
              "word": "to",
              "charStart": 24,
              "charEnd": 26,
              "startMs": 1520,
              "endMs": 1900
            },
            {
              "word": "smell",
              "charStart": 27,
              "charEnd": 32,
              "startMs": 1900,
              "endMs": 2180
            },
            {
              "word": "the",
              "charStart": 33,
              "charEnd": 36,
              "startMs": 2180,
              "endMs": 2440
            },
            {
              "word": "fresh",
              "charStart": 37,
              "charEnd": 42,
              "startMs": 2440,
              "endMs": 2740
            },
            {
              "word": "herbs",
              "charStart": 43,
              "charEnd": 48,
              "startMs": 2740,
              "endMs": 3120
            }
          ]
        }
      ]
    },
    {
      "sentences": [
        {
          "text": "Our plan turned an empty roof into a shared garden.",
          "translation_ko": "우리의 계획은 빈 옥상을 함께 쓰는 정원으로 바꾸었어요.",
          "audio": "/seed/the-rooftop-garden-plan/audio/p10-s1.mp3",
          "wordTimings": [
            {
              "word": "Our",
              "charStart": 0,
              "charEnd": 3,
              "startMs": 0,
              "endMs": 300
            },
            {
              "word": "plan",
              "charStart": 4,
              "charEnd": 8,
              "startMs": 300,
              "endMs": 620
            },
            {
              "word": "turned",
              "charStart": 9,
              "charEnd": 15,
              "startMs": 620,
              "endMs": 920
            },
            {
              "word": "an",
              "charStart": 16,
              "charEnd": 18,
              "startMs": 920,
              "endMs": 1200
            },
            {
              "word": "empty",
              "charStart": 19,
              "charEnd": 24,
              "startMs": 1200,
              "endMs": 1460
            },
            {
              "word": "roof",
              "charStart": 25,
              "charEnd": 29,
              "startMs": 1460,
              "endMs": 1760
            },
            {
              "word": "into",
              "charStart": 30,
              "charEnd": 34,
              "startMs": 1760,
              "endMs": 2120
            },
            {
              "word": "a",
              "charStart": 35,
              "charEnd": 36,
              "startMs": 2120,
              "endMs": 2380
            },
            {
              "word": "shared",
              "charStart": 37,
              "charEnd": 43,
              "startMs": 2380,
              "endMs": 2620
            },
            {
              "word": "garden",
              "charStart": 44,
              "charEnd": 50,
              "startMs": 2620,
              "endMs": 2900
            }
          ]
        }
      ]
    }
  ],
  "words": {},
  "quiz": [
    {
      "question_ko": "옥상 정원 계획에서 중심이 되는 것은 무엇인가요?",
      "type": "mc",
      "options": [
        "옥상 정원을 만드는 아이들",
        "낡은 시계",
        "큰 가방",
        "빨간 버스"
      ],
      "answerIndex": 0,
      "explain_ko": "옥상 정원을 만드는 아이들이 이야기의 중심이에요."
    },
    {
      "question_ko": "이야기는 주로 어디에서 펼쳐지나요?",
      "type": "mc",
      "options": [
        "햇빛 드는 옥상",
        "운동장",
        "병원",
        "기차역"
      ],
      "answerIndex": 0,
      "explain_ko": "햇빛 드는 옥상에서 중요한 일이 일어나요."
    },
    {
      "question_ko": "주인공이 만난 문제는 무엇인가요?",
      "type": "mc",
      "options": [
        "바람이 세고 물을 옮기기 어려웠어요",
        "비밀 편지를 잃었어요",
        "문이 잠겼어요",
        "간식이 없었어요"
      ],
      "answerIndex": 0,
      "explain_ko": "바람이 세고 물을 옮기기 어려웠어요"
    },
    {
      "question_ko": "누가 또는 무엇이 도움을 주었나요?",
      "type": "mc",
      "options": [
        "역할 나누기와 무거운 물통",
        "검은 구름",
        "빈 상자",
        "낯선 모자"
      ],
      "answerIndex": 0,
      "explain_ko": "역할 나누기와 무거운 물통이 해결을 도와요."
    },
    {
      "question_ko": "이야기가 알려 주는 마음은 무엇인가요?",
      "type": "mc",
      "options": [
        "빨리 이기는 마음",
        "아무것도 하지 않는 마음",
        "혼자 숨는 마음",
        "계획하고 나누어 일하는 마음"
      ],
      "answerIndex": 3,
      "explain_ko": "계획하고 나누어 일하는 마음을 배워요."
    }
  ]
}
